grnpy.py
grnpy-0.0.9.dist-info/METADATA
grnpy-0.0.9.dist-info/WHEEL
grnpy-0.0.9.dist-info/top_level.txt
grnpy-0.0.9.dist-info/RECORD
