Metadata-Version: 2.1
Name: grnpy
Version: 0.0.9
Summary: Added support for list representation
Author: Tim Zhang
Classifier: Programming Language :: Python :: 3
Classifier: License :: OSI Approved :: MIT License
Classifier: Operating System :: OS Independent
Requires-Python: >=3.6
